httpx_aiohttp_transport/__init__.py
httpx_aiohttptransport-0.2.1.dist-info/LICENSE
httpx_aiohttptransport-0.2.1.dist-info/METADATA
httpx_aiohttptransport-0.2.1.dist-info/WHEEL
httpx_aiohttptransport-0.2.1.dist-info/RECORD
