Metadata-Version: 2.3
Name: httpx-aiohttptransport
Version: 0.2.1
Summary: Use `aiohttp` with `httpx` Interface
License: MIT
Author: Zeyan Li
Author-email: li_zeyan@icloud.com
Requires-Python: >=3.9
Classifier: License :: OSI Approved :: MIT License
Classifier: Programming Language :: Python :: 3
Classifier: Programming Language :: Python :: 3.9
Classifier: Programming Language :: Python :: 3.10
Classifier: Programming Language :: Python :: 3.11
Classifier: Programming Language :: Python :: 3.12
Classifier: Programming Language :: Python :: 3.13
Requires-Dist: aiohttp (>=3.11.11,<4.0.0)
Requires-Dist: httpx (>=0.28.1,<0.29.0)
